inverseui/__init__.py
inverseui/auth.py
inverseui/backend.py
inverseui/cli.py
inverseui/config.py
inverseui/executor.py
inverseui/runner.py
inverseui/utils/__init__.py
inverseui/utils/keychain.py
inverseui/utils/logging.py
inverseui-0.0.2.dist-info/METADATA
inverseui-0.0.2.dist-info/WHEEL
inverseui-0.0.2.dist-info/entry_points.txt
inverseui-0.0.2.dist-info/top_level.txt
inverseui-0.0.2.dist-info/RECORD
